pywbemtools/__init__.py
pywbemtools/_click_extensions.py
pywbemtools/_common_cmd_actions.py
pywbemtools/_options.py
pywbemtools/_output_formatting.py
pywbemtools/_utils.py
pywbemtools/_version.py
pywbemtools/_version_scm.py
pywbemtools/pywbemcli/__init__.py
pywbemtools/pywbemcli/_association_shrub.py
pywbemtools/pywbemcli/_cimvalueformatter.py
pywbemtools/pywbemcli/_cmd_class.py
pywbemtools/pywbemcli/_cmd_connection.py
pywbemtools/pywbemcli/_cmd_docs.py
pywbemtools/pywbemcli/_cmd_help.py
pywbemtools/pywbemcli/_cmd_instance.py
pywbemtools/pywbemcli/_cmd_namespace.py
pywbemtools/pywbemcli/_cmd_profile.py
pywbemtools/pywbemcli/_cmd_qualifier.py
pywbemtools/pywbemcli/_cmd_server.py
pywbemtools/pywbemcli/_cmd_statistics.py
pywbemtools/pywbemcli/_cmd_subscription.py
pywbemtools/pywbemcli/_cmd_tabcompletion.py.save
pywbemtools/pywbemcli/_common.py
pywbemtools/pywbemcli/_common_cmd_functions.py
pywbemtools/pywbemcli/_common_options.py
pywbemtools/pywbemcli/_connection_repository.py
pywbemtools/pywbemcli/_context_obj.py
pywbemtools/pywbemcli/_display_cimobjects.py
pywbemtools/pywbemcli/_displaytree.py
pywbemtools/pywbemcli/_pywbem_server.py
pywbemtools/pywbemcli/_pywbemcli_operations.py
pywbemtools/pywbemcli/_warnings.py
pywbemtools/pywbemcli/config.py
pywbemtools/pywbemcli/pywbemcli.py
pywbemtools/pywbemcli/mockscripts/__init__.py
pywbemtools/pywbemlistener/__init__.py
pywbemtools/pywbemlistener/_cmd_docs.py
pywbemtools/pywbemlistener/_cmd_help.py
pywbemtools/pywbemlistener/_cmd_listener.py
pywbemtools/pywbemlistener/_config.py
pywbemtools/pywbemlistener/_context_obj.py
pywbemtools/pywbemlistener/pywbemlistener.py
pywbemtools-1.3.1.dist-info/licenses/AUTHORS
pywbemtools-1.3.1.dist-info/licenses/LICENSE.txt
pywbemtools-1.3.1.dist-info/METADATA
pywbemtools-1.3.1.dist-info/WHEEL
pywbemtools-1.3.1.dist-info/entry_points.txt
pywbemtools-1.3.1.dist-info/top_level.txt
pywbemtools-1.3.1.dist-info/zip-safe
pywbemtools-1.3.1.dist-info/RECORD
