Metadata-Version: 2.4
Name: pywbemtools
Version: 1.3.1
Summary: Python client tools to work with WBEM Servers using the PyWBEM API.
Home-page: https://github.com/pywbem/pywbemtools
Author: Karl Schopmeyer, Andreas Maier
Author-email: k.schopmeyer@swbell.net, maiera@de.ibm.com
Maintainer: Karl Schopmeyer, Andreas Maier
Maintainer-email: k.schopmeyer@swbell.net, maiera@de.ibm.com
License: Apache License, Version 2.0
Project-URL: Bug Tracker, https://github.com/pywbem/pywbemtools/issues
Project-URL: Documentation, https://pywbemtools.readthedocs.io/en/latest/
Project-URL: Source Code, https://github.com/pywbem/pywbemtools
Platform: any
Classifier: Development Status :: 5 - Production/Stable
Classifier: Environment :: Console
Classifier: Intended Audience :: Developers
Classifier: Intended Audience :: Information Technology
Classifier: License :: OSI Approved :: Apache Software License
Classifier: Operating System :: OS Independent
Classifier: Programming Language :: Python
Classifier: Programming Language :: Python :: 2
Classifier: Programming Language :: Python :: 2.7
Classifier: Programming Language :: Python :: 3
Classifier: Programming Language :: Python :: 3.6
Classifier: Programming Language :: Python :: 3.7
Classifier: Programming Language :: Python :: 3.8
Classifier: Programming Language :: Python :: 3.9
Classifier: Programming Language :: Python :: 3.10
Classifier: Programming Language :: Python :: 3.11
Classifier: Programming Language :: Python :: 3.12
Requires-Python: >=2.7, !=3.0.*, !=3.1.*, !=3.2.*, !=3.3.*, !=3.4.*, !=3.5.*
License-File: LICENSE.txt
License-File: AUTHORS
Requires-Dist: pywbem>=1.7.2
Requires-Dist: nocaselist>=1.0.3
Requires-Dist: nocasedict>=1.0.1
Requires-Dist: six>=1.14.0; python_version <= "3.9"
Requires-Dist: six>=1.16.0; python_version >= "3.10"
Requires-Dist: Click<8.0,>=7.1.1; python_version == "2.7"
Requires-Dist: Click>=8.0.2; python_version >= "3.6"
Requires-Dist: click-spinner>=0.1.8; python_version <= "3.11"
Requires-Dist: click-spinner>=0.1.10; python_version >= "3.12"
Requires-Dist: click-repl<0.3.0,>=0.1.6; python_version == "2.7"
Requires-Dist: click-repl<0.3.0,>=0.2; python_version >= "3.6"
Requires-Dist: asciitree>=0.3.3
Requires-Dist: tabulate>=0.8.2; python_version <= "3.9"
Requires-Dist: tabulate>=0.8.8; python_version >= "3.10"
Requires-Dist: toposort<=1.7,>=1.6; python_version <= "3.7"
Requires-Dist: toposort>=1.6; python_version >= "3.8"
Requires-Dist: psutil>=5.5.0; python_version <= "3.7"
Requires-Dist: psutil~=6.1.0; python_version >= "3.8"
Requires-Dist: prompt-toolkit<3.0.0,>=1.0.15; python_version == "2.7"
Requires-Dist: prompt-toolkit>=3.0.13; python_version >= "3.6"
Requires-Dist: PyYAML>=5.3.1; python_version <= "3.5"
Requires-Dist: PyYAML!=5.4.0,!=5.4.1,>=5.3.1; python_version >= "3.6" and python_version <= "3.11"
Requires-Dist: PyYAML!=5.4.0,!=5.4.1,!=6.0.0,>=5.3.1; python_version >= "3.12"
Requires-Dist: yamlloader>=0.5.5
Requires-Dist: packaging>=19.0; python_version == "2.7"
Requires-Dist: packaging>=21.0; python_version == "3.6"
Requires-Dist: packaging>=22.0; python_version >= "3.7"
Requires-Dist: mock<4.0.0,>=3.0.0; python_version < "3.6"
Requires-Dist: mock>=3.0.0; python_version >= "3.6"
Requires-Dist: funcsigs>=1.0.2; python_version == "2.7"
Requires-Dist: pyparsing<3.0.0,>=2.3.1; python_version == "2.7"
Requires-Dist: pyparsing>=2.3.1; python_version >= "3.6"
Requires-Dist: urllib3<2.0.0,>=1.26.20; python_version == "2.7"
Requires-Dist: urllib3<2.0.0,>=1.26.20; python_version == "3.6"
Requires-Dist: urllib3>=2.0.7; python_version == "3.7"
Requires-Dist: urllib3>=2.2.3; python_version == "3.8"
Requires-Dist: urllib3>=2.5.0; python_version >= "3.9"
Dynamic: author
Dynamic: author-email
Dynamic: classifier
Dynamic: description
Dynamic: description-content-type
Dynamic: home-page
Dynamic: license
Dynamic: license-file
Dynamic: maintainer
Dynamic: maintainer-email
Dynamic: platform
Dynamic: project-url
Dynamic: requires-dist
Dynamic: requires-python
Dynamic: summary
